scale_egp/__init__.py
scale_egp/cli/__init__.py
scale_egp/cli/cli_main.py
scale_egp/cli/collections.py
scale_egp/cli/formatter.py
scale_egp/cli/model_instance_description.py
scale_egp/cli/parser.py
scale_egp/cli/vpc_setup_commands.py
scale_egp/exceptions.py
scale_egp/sdk/__init__.py
scale_egp/sdk/client.py
scale_egp/sdk/collections/__init__.py
scale_egp/sdk/collections/application_specs.py
scale_egp/sdk/collections/chunks.py
scale_egp/sdk/collections/completions.py
scale_egp/sdk/collections/evaluation_configs.py
scale_egp/sdk/collections/evaluation_datasets.py
scale_egp/sdk/collections/evaluations.py
scale_egp/sdk/collections/fine_tuning.py
scale_egp/sdk/collections/knowledge_bases.py
scale_egp/sdk/collections/model_groups.py
scale_egp/sdk/collections/model_templates.py
scale_egp/sdk/collections/models.py
scale_egp/sdk/collections/question_sets.py
scale_egp/sdk/collections/questions.py
scale_egp/sdk/collections/users.py
scale_egp/sdk/constants/__init__.py
scale_egp/sdk/constants/model_schemas.py
scale_egp/sdk/enums.py
scale_egp/sdk/models/__init__.py
scale_egp/sdk/models/completions/chat_completion_models.py
scale_egp/sdk/models/fine_tuning_jobs.py
scale_egp/sdk/models/model_enums.py
scale_egp/sdk/models/model_vendor_configuration.py
scale_egp/sdk/types/__init__.py
scale_egp/sdk/types/agents.py
scale_egp/sdk/types/application_specs.py
scale_egp/sdk/types/chunks.py
scale_egp/sdk/types/completions.py
scale_egp/sdk/types/embeddings.py
scale_egp/sdk/types/evaluation_configs.py
scale_egp/sdk/types/evaluation_dataset_test_cases.py
scale_egp/sdk/types/evaluation_datasets.py
scale_egp/sdk/types/evaluation_test_case_results.py
scale_egp/sdk/types/evaluations.py
scale_egp/sdk/types/fine_tuning.py
scale_egp/sdk/types/knowledge_base_artifacts.py
scale_egp/sdk/types/knowledge_base_chunks.py
scale_egp/sdk/types/knowledge_base_uploads.py
scale_egp/sdk/types/knowledge_bases.py
scale_egp/sdk/types/memory_strategy.py
scale_egp/sdk/types/message.py
scale_egp-1.1.15.dist-info/METADATA
scale_egp-1.1.15.dist-info/WHEEL
scale_egp-1.1.15.dist-info/entry_points.txt
scale_egp-1.1.15.dist-info/RECORD
