Metadata-Version: 2.1
Name: scale-egp
Version: 1.1.15
Summary: SDK for Scale SGP API
Home-page: https://scaleapi.github.io/sgp-py/
License: Apache 2.0 modified with Commons Clause
Author: Scale SGP team
Requires-Python: >=3.8,<4.0
Classifier: License :: Other/Proprietary License
Classifier: Programming Language :: Python :: 3
Classifier: Programming Language :: Python :: 3.8
Classifier: Programming Language :: Python :: 3.9
Classifier: Programming Language :: Python :: 3.10
Classifier: Programming Language :: Python :: 3.11
Classifier: Programming Language :: Python :: 3.12
Requires-Dist: argh (>=0.30.4,<0.31.0)
Requires-Dist: boto3 (>=1.34.81,<2.0.0)
Requires-Dist: docker (>=7.0.0,<8.0.0)
Requires-Dist: docutils (==0.20.1)
Requires-Dist: fastjsonschema (>=2.19.0,<3.0.0)
Requires-Dist: httpx (>0.25.0,<1.0)
Requires-Dist: mock (>=4.0.3,<5.0.0)
Requires-Dist: pydantic (>=1.10.11)
Requires-Dist: requests (>=2.22)
Requires-Dist: rich (>=13.7.0,<14.0.0)
Requires-Dist: strenum (>=0.4.15,<0.5.0)
Project-URL: Repository, https://github.com/scaleapi/egp-py
